{"cameraMode":{"drawMode":0,"name":"Shaded","section":"Shading Mode"},"sceneLighting":false,"audioPlay":false,"sceneViewState":{"m_AlwaysRefresh":false,"showFog":true,"showSkybox":false,"showFlares":true,"showImageEffects":true,"showParticleSystems":true,"showVisualEffectGraphs":true,"m_FxEnabled":true},"in2DMode":false,"pivot":{"x":5.247001647949219,"y":-3.3547606468200685,"z":1.689585566520691},"rotation":{"x":-0.3255549371242523,"y":0.020263146609067918,"z":-0.006439655087888241,"w":-0.9448225498199463},"size":10.0,"orthographic":false}